<?xml version="1.0"?>
<Cisco-IOS-XR-segment-routing-ms-oper ns="http://cisco.com/ns/yang/Cisco-IOS-XR-segment-routing-ms-oper" revision="2017-09-07">
  <files>
    <file revision="2017-09-07" submodule="false">Cisco-IOS-XR-segment-routing-ms-oper.yang</file>
    <file revision="2017-09-07" submodule="true">Cisco-IOS-XR-segment-routing-ms-oper-sub3.yang</file>
    <file revision="2017-09-07" submodule="true">Cisco-IOS-XR-segment-routing-ms-oper-sub2.yang</file>
    <file revision="2017-09-07" submodule="true">Cisco-IOS-XR-segment-routing-ms-oper-sub1.yang</file>
  </files>
  <prefix>segment-routing-ms-oper</prefix>
  <organization>Cisco Systems, Inc.</organization>
  <import prefix="xr">Cisco-IOS-XR-types</import>
  <import prefix="inet">ietf-inet-types</import>
  <typedef name="Sid-type-enum">
    <xr-sch-type>Enum</xr-sch-type>
    <type node="enumeration">
      <enum value="1">absolute</enum>
      <enum value="2">index</enum>
    </type>
  </typedef>
  <typedef name="Srms-mi-flag-e-b">
    <type node="enumeration">
      <enum value="0">false</enum>
      <enum value="1">true</enum>
    </type>
  </typedef>
  <typedef name="In6-addr-t-b">
    <xr-bag-primitive-type>in6_addr_t</xr-bag-primitive-type>
    <type>
      <type-name>inet:ipv6-address</type-name>
    </type>
  </typedef>
  <typedef name="Srms-mi-af-e-b">
    <type node="enumeration">
      <enum value="0">none</enum>
      <enum value="1">ipv4</enum>
      <enum value="2">ipv6</enum>
    </type>
  </typedef>
  <typedef name="Srms-mi-src-e-b">
    <type node="enumeration">
      <enum value="0">none</enum>
      <enum value="1">local</enum>
      <enum value="2">remote</enum>
    </type>
  </typedef>
  <typedef name="Srms-af">
    <type node="enumeration">
      <enum value="0">none</enum>
      <enum value="1">ipv4</enum>
      <enum value="2">ipv6</enum>
    </type>
  </typedef>
  <srms config="false" is-key="false" node="container" presence="false">
    <xr-path>/oper/srms/gl/active/</xr-path>
    <xr-xml-map>srms_oper:SRMS</xr-xml-map>
    <xr-task>basic-services</xr-task>
    <mapping config="false" is-key="false" node="container" presence="false">
      <xr-path>/oper/srms/gl/active/sid/</xr-path>
      <xr-xml-map>srms_oper:Mapping</xr-xml-map>
      <xr-task>basic-services</xr-task>
      <mapping-ipv4 config="false" is-key="false" node="container" presence="false">
        <xr-path>/oper/srms/gl/active/sid/ipv4/</xr-path>
        <xr-xml-map>srms_oper:MappingIpv4</xr-xml-map>
        <xr-task>basic-services</xr-task>
        <mapping-mi config="false" node="list">
          <xr-path>/oper/srms/gl/active/sid/ipv4/&lt;srms_oper_MappingMi_IP&gt;,&lt;srms_oper_MappingMi_Prefix&gt;</xr-path>
          <xr-xml-map>srms_oper:MappingMi</xr-xml-map>
          <xr-task>basic-services</xr-task>
          <xr-bag-grp-name>srms_mi_t_b</xr-bag-grp-name>
          <xr-bag>srms_show.bag</xr-bag>
          <ip config="false" is-key="true" is-yang-key="false" node="leaf">
            <xr-primitive-type>string</xr-primitive-type>
            <xr-path>/oper/srms/gl/active/sid/ipv4/&lt;srms_oper_MappingMi_IP&gt;,&lt;srms_oper_MappingMi_Prefix&gt;</xr-path>
            <xr-xml-map>srms_oper:IP</xr-xml-map>
            <xr-task>basic-services</xr-task>
            <xr-sch-type>String</xr-sch-type>
            <xr-sch-arg-name>&lt;srms_oper_MappingMi_IP&gt;</xr-sch-arg-name>
            <type>
              <type-name>xr:Cisco-ios-xr-string</type-name>
            </type>
          </ip>
          <prefix config="false" is-key="true" is-yang-key="false" node="leaf">
            <xr-primitive-type>uint32</xr-primitive-type>
            <xr-path>/oper/srms/gl/active/sid/ipv4/&lt;srms_oper_MappingMi_IP&gt;,&lt;srms_oper_MappingMi_Prefix&gt;</xr-path>
            <xr-xml-map>srms_oper:Prefix</xr-xml-map>
            <xr-task>basic-services</xr-task>
            <xr-sch-type>Integer</xr-sch-type>
            <xr-sch-arg-name>&lt;srms_oper_MappingMi_Prefix&gt;</xr-sch-arg-name>
            <type>
              <type-name>uint32</type-name>
            </type>
          </prefix>
          <addr config="false" is-key="false" node="container" presence="false">
            <xr-path>/oper/srms/gl/active/sid/ipv4/&lt;srms_oper_MappingMi_IP&gt;,&lt;srms_oper_MappingMi_Prefix&gt;~srms_mi_t_b.addr</xr-path>
            <xr-task>basic-services</xr-task>
            <xr-bag-version>1 1</xr-bag-version>
            <af config="false" is-key="false" is-yang-key="false" node="leaf">
              <xr-path>/oper/srms/gl/active/sid/ipv4/&lt;srms_oper_MappingMi_IP&gt;,&lt;srms_oper_MappingMi_Prefix&gt;~srms_mi_t_b.addr.AF</xr-path>
              <xr-xml-map>srms_show:AF</xr-xml-map>
              <xr-task>basic-services</xr-task>
              <xr-bag-primitive-type>int</xr-bag-primitive-type>
              <xr-bag-version>1 1</xr-bag-version>
              <type>
                <type-name>Srms-mi-af-e-b</type-name>
              </type>
            </af>
            <ipv4 config="false" is-key="false" is-yang-key="false" node="leaf">
              <xr-path>/oper/srms/gl/active/sid/ipv4/&lt;srms_oper_MappingMi_IP&gt;,&lt;srms_oper_MappingMi_Prefix&gt;~srms_mi_t_b.addr.IPv4</xr-path>
              <xr-xml-map>srms_show:IPv4</xr-xml-map>
              <xr-task>basic-services</xr-task>
              <xr-bag-primitive-type>in_addr_t</xr-bag-primitive-type>
              <xr-bag-version>1 1</xr-bag-version>
              <when>../af = 'ipv4'</when>
              <type>
                <type-name>inet:ipv4-address</type-name>
              </type>
            </ipv4>
            <ipv6 config="false" is-key="false" is-yang-key="false" node="leaf">
              <xr-path>/oper/srms/gl/active/sid/ipv4/&lt;srms_oper_MappingMi_IP&gt;,&lt;srms_oper_MappingMi_Prefix&gt;~srms_mi_t_b.addr.IPv6</xr-path>
              <xr-xml-map>srms_show:IPv6</xr-xml-map>
              <xr-task>basic-services</xr-task>
              <xr-bag-primitive-type>in6_addr_t</xr-bag-primitive-type>
              <xr-bag-version>1 1</xr-bag-version>
              <when>../af = 'ipv6'</when>
              <type>
                <type-name>In6-addr-t-b</type-name>
              </type>
            </ipv6>
          </addr>
          <src config="false" is-key="false" is-yang-key="false" node="leaf">
            <xr-path>/oper/srms/gl/active/sid/ipv4/&lt;srms_oper_MappingMi_IP&gt;,&lt;srms_oper_MappingMi_Prefix&gt;~srms_mi_t_b.src</xr-path>
            <xr-xml-map>srms_show:src</xr-xml-map>
            <xr-task>basic-services</xr-task>
            <xr-bag-primitive-type>int</xr-bag-primitive-type>
            <xr-bag-version>1 1</xr-bag-version>
            <type>
              <type-name>Srms-mi-src-e-b</type-name>
            </type>
          </src>
          <router config="false" is-key="false" is-yang-key="false" node="leaf">
            <xr-path>/oper/srms/gl/active/sid/ipv4/&lt;srms_oper_MappingMi_IP&gt;,&lt;srms_oper_MappingMi_Prefix&gt;~srms_mi_t_b.router</xr-path>
            <xr-xml-map>srms_show:router</xr-xml-map>
            <xr-task>basic-services</xr-task>
            <xr-bag-primitive-type>string</xr-bag-primitive-type>
            <xr-bag-version>1 1</xr-bag-version>
            <type length="0..30">
              <type-name>string</type-name>
            </type>
          </router>
          <area config="false" is-key="false" is-yang-key="false" node="leaf">
            <xr-path>/oper/srms/gl/active/sid/ipv4/&lt;srms_oper_MappingMi_IP&gt;,&lt;srms_oper_MappingMi_Prefix&gt;~srms_mi_t_b.area</xr-path>
            <xr-xml-map>srms_show:area</xr-xml-map>
            <xr-task>basic-services</xr-task>
            <xr-bag-primitive-type>string</xr-bag-primitive-type>
            <xr-bag-version>1 1</xr-bag-version>
            <type length="0..30">
              <type-name>string</type-name>
            </type>
          </area>
          <prefix-xr config="false" is-key="false" is-yang-key="false" node="leaf">
            <xr-path>/oper/srms/gl/active/sid/ipv4/&lt;srms_oper_MappingMi_IP&gt;,&lt;srms_oper_MappingMi_Prefix&gt;~srms_mi_t_b.prefix</xr-path>
            <xr-xml-map>srms_show:prefix-xr</xr-xml-map>
            <xr-task>basic-services</xr-task>
            <xr-bag-primitive-type>uint8_t</xr-bag-primitive-type>
            <xr-bag-version>1 1</xr-bag-version>
            <type>
              <type-name>uint8</type-name>
            </type>
          </prefix-xr>
          <sid-start config="false" is-key="false" is-yang-key="false" node="leaf">
            <xr-path>/oper/srms/gl/active/sid/ipv4/&lt;srms_oper_MappingMi_IP&gt;,&lt;srms_oper_MappingMi_Prefix&gt;~srms_mi_t_b.sid_start</xr-path>
            <xr-xml-map>srms_show:sid_start</xr-xml-map>
            <xr-task>basic-services</xr-task>
            <xr-bag-primitive-type>uint32_t</xr-bag-primitive-type>
            <xr-bag-version>1 1</xr-bag-version>
            <type>
              <type-name>uint32</type-name>
            </type>
          </sid-start>
          <sid-count config="false" is-key="false" is-yang-key="false" node="leaf">
            <xr-path>/oper/srms/gl/active/sid/ipv4/&lt;srms_oper_MappingMi_IP&gt;,&lt;srms_oper_MappingMi_Prefix&gt;~srms_mi_t_b.sid_count</xr-path>
            <xr-xml-map>srms_show:sid_count</xr-xml-map>
            <xr-task>basic-services</xr-task>
            <xr-bag-primitive-type>uint32_t</xr-bag-primitive-type>
            <xr-bag-version>1 1</xr-bag-version>
            <type>
              <type-name>uint32</type-name>
            </type>
          </sid-count>
          <last-prefix config="false" is-key="false" is-yang-key="false" node="leaf">
            <xr-path>/oper/srms/gl/active/sid/ipv4/&lt;srms_oper_MappingMi_IP&gt;,&lt;srms_oper_MappingMi_Prefix&gt;~srms_mi_t_b.last_prefix</xr-path>
            <xr-xml-map>srms_show:last_prefix</xr-xml-map>
            <xr-task>basic-services</xr-task>
            <xr-bag-primitive-type>string</xr-bag-primitive-type>
            <xr-bag-version>1 1</xr-bag-version>
            <type length="0..50">
              <type-name>string</type-name>
            </type>
          </last-prefix>
          <last-sid-index config="false" is-key="false" is-yang-key="false" node="leaf">
            <xr-path>/oper/srms/gl/active/sid/ipv4/&lt;srms_oper_MappingMi_IP&gt;,&lt;srms_oper_MappingMi_Prefix&gt;~srms_mi_t_b.last_sid_index</xr-path>
            <xr-xml-map>srms_show:last_sid_index</xr-xml-map>
            <xr-task>basic-services</xr-task>
            <xr-bag-primitive-type>uint32_t</xr-bag-primitive-type>
            <xr-bag-version>1 1</xr-bag-version>
            <type>
              <type-name>uint32</type-name>
            </type>
          </last-sid-index>
          <flag-attached config="false" is-key="false" is-yang-key="false" node="leaf">
            <xr-path>/oper/srms/gl/active/sid/ipv4/&lt;srms_oper_MappingMi_IP&gt;,&lt;srms_oper_MappingMi_Prefix&gt;~srms_mi_t_b.flag_attached</xr-path>
            <xr-xml-map>srms_show:flag_attached</xr-xml-map>
            <xr-task>basic-services</xr-task>
            <xr-bag-primitive-type>int</xr-bag-primitive-type>
            <xr-bag-version>1 1</xr-bag-version>
            <type>
              <type-name>Srms-mi-flag-e-b</type-name>
            </type>
          </flag-attached>
        </mapping-mi>
      </mapping-ipv4>
      <mapping-ipv6 config="false" is-key="false" node="container" presence="false">
        <xr-path>/oper/srms/gl/active/sid/ipv6/</xr-path>
        <xr-xml-map>srms_oper:MappingIpv6</xr-xml-map>
        <xr-task>basic-services</xr-task>
        <mapping-mi config="false" node="list">
          <xr-path>/oper/srms/gl/active/sid/ipv6/&lt;srms_oper_MappingMi_IP&gt;,&lt;srms_oper_MappingMi_Prefix&gt;</xr-path>
          <xr-xml-map>srms_oper:MappingMi</xr-xml-map>
          <xr-task>basic-services</xr-task>
          <xr-bag-grp-name>srms_mi_t_b</xr-bag-grp-name>
          <xr-bag>srms_show.bag</xr-bag>
          <ip config="false" is-key="true" is-yang-key="false" node="leaf">
            <xr-primitive-type>string</xr-primitive-type>
            <xr-path>/oper/srms/gl/active/sid/ipv6/&lt;srms_oper_MappingMi_IP&gt;,&lt;srms_oper_MappingMi_Prefix&gt;</xr-path>
            <xr-xml-map>srms_oper:IP</xr-xml-map>
            <xr-task>basic-services</xr-task>
            <xr-sch-type>String</xr-sch-type>
            <xr-sch-arg-name>&lt;srms_oper_MappingMi_IP&gt;</xr-sch-arg-name>
            <type>
              <type-name>xr:Cisco-ios-xr-string</type-name>
            </type>
          </ip>
          <prefix config="false" is-key="true" is-yang-key="false" node="leaf">
            <xr-primitive-type>uint32</xr-primitive-type>
            <xr-path>/oper/srms/gl/active/sid/ipv6/&lt;srms_oper_MappingMi_IP&gt;,&lt;srms_oper_MappingMi_Prefix&gt;</xr-path>
            <xr-xml-map>srms_oper:Prefix</xr-xml-map>
            <xr-task>basic-services</xr-task>
            <xr-sch-type>Integer</xr-sch-type>
            <xr-sch-arg-name>&lt;srms_oper_MappingMi_Prefix&gt;</xr-sch-arg-name>
            <type>
              <type-name>uint32</type-name>
            </type>
          </prefix>
          <addr config="false" is-key="false" node="container" presence="false">
            <xr-path>/oper/srms/gl/active/sid/ipv6/&lt;srms_oper_MappingMi_IP&gt;,&lt;srms_oper_MappingMi_Prefix&gt;~srms_mi_t_b.addr</xr-path>
            <xr-task>basic-services</xr-task>
            <xr-bag-version>1 1</xr-bag-version>
            <af config="false" is-key="false" is-yang-key="false" node="leaf">
              <xr-path>/oper/srms/gl/active/sid/ipv6/&lt;srms_oper_MappingMi_IP&gt;,&lt;srms_oper_MappingMi_Prefix&gt;~srms_mi_t_b.addr.AF</xr-path>
              <xr-xml-map>srms_show:AF</xr-xml-map>
              <xr-task>basic-services</xr-task>
              <xr-bag-primitive-type>int</xr-bag-primitive-type>
              <xr-bag-version>1 1</xr-bag-version>
              <type>
                <type-name>Srms-mi-af-e-b</type-name>
              </type>
            </af>
            <ipv4 config="false" is-key="false" is-yang-key="false" node="leaf">
              <xr-path>/oper/srms/gl/active/sid/ipv6/&lt;srms_oper_MappingMi_IP&gt;,&lt;srms_oper_MappingMi_Prefix&gt;~srms_mi_t_b.addr.IPv4</xr-path>
              <xr-xml-map>srms_show:IPv4</xr-xml-map>
              <xr-task>basic-services</xr-task>
              <xr-bag-primitive-type>in_addr_t</xr-bag-primitive-type>
              <xr-bag-version>1 1</xr-bag-version>
              <when>../af = 'ipv4'</when>
              <type>
                <type-name>inet:ipv4-address</type-name>
              </type>
            </ipv4>
            <ipv6 config="false" is-key="false" is-yang-key="false" node="leaf">
              <xr-path>/oper/srms/gl/active/sid/ipv6/&lt;srms_oper_MappingMi_IP&gt;,&lt;srms_oper_MappingMi_Prefix&gt;~srms_mi_t_b.addr.IPv6</xr-path>
              <xr-xml-map>srms_show:IPv6</xr-xml-map>
              <xr-task>basic-services</xr-task>
              <xr-bag-primitive-type>in6_addr_t</xr-bag-primitive-type>
              <xr-bag-version>1 1</xr-bag-version>
              <when>../af = 'ipv6'</when>
              <type>
                <type-name>In6-addr-t-b</type-name>
              </type>
            </ipv6>
          </addr>
          <src config="false" is-key="false" is-yang-key="false" node="leaf">
            <xr-path>/oper/srms/gl/active/sid/ipv6/&lt;srms_oper_MappingMi_IP&gt;,&lt;srms_oper_MappingMi_Prefix&gt;~srms_mi_t_b.src</xr-path>
            <xr-xml-map>srms_show:src</xr-xml-map>
            <xr-task>basic-services</xr-task>
            <xr-bag-primitive-type>int</xr-bag-primitive-type>
            <xr-bag-version>1 1</xr-bag-version>
            <type>
              <type-name>Srms-mi-src-e-b</type-name>
            </type>
          </src>
          <router config="false" is-key="false" is-yang-key="false" node="leaf">
            <xr-path>/oper/srms/gl/active/sid/ipv6/&lt;srms_oper_MappingMi_IP&gt;,&lt;srms_oper_MappingMi_Prefix&gt;~srms_mi_t_b.router</xr-path>
            <xr-xml-map>srms_show:router</xr-xml-map>
            <xr-task>basic-services</xr-task>
            <xr-bag-primitive-type>string</xr-bag-primitive-type>
            <xr-bag-version>1 1</xr-bag-version>
            <type length="0..30">
              <type-name>string</type-name>
            </type>
          </router>
          <area config="false" is-key="false" is-yang-key="false" node="leaf">
            <xr-path>/oper/srms/gl/active/sid/ipv6/&lt;srms_oper_MappingMi_IP&gt;,&lt;srms_oper_MappingMi_Prefix&gt;~srms_mi_t_b.area</xr-path>
            <xr-xml-map>srms_show:area</xr-xml-map>
            <xr-task>basic-services</xr-task>
            <xr-bag-primitive-type>string</xr-bag-primitive-type>
            <xr-bag-version>1 1</xr-bag-version>
            <type length="0..30">
              <type-name>string</type-name>
            </type>
          </area>
          <prefix-xr config="false" is-key="false" is-yang-key="false" node="leaf">
            <xr-path>/oper/srms/gl/active/sid/ipv6/&lt;srms_oper_MappingMi_IP&gt;,&lt;srms_oper_MappingMi_Prefix&gt;~srms_mi_t_b.prefix</xr-path>
            <xr-xml-map>srms_show:prefix-xr</xr-xml-map>
            <xr-task>basic-services</xr-task>
            <xr-bag-primitive-type>uint8_t</xr-bag-primitive-type>
            <xr-bag-version>1 1</xr-bag-version>
            <type>
              <type-name>uint8</type-name>
            </type>
          </prefix-xr>
          <sid-start config="false" is-key="false" is-yang-key="false" node="leaf">
            <xr-path>/oper/srms/gl/active/sid/ipv6/&lt;srms_oper_MappingMi_IP&gt;,&lt;srms_oper_MappingMi_Prefix&gt;~srms_mi_t_b.sid_start</xr-path>
            <xr-xml-map>srms_show:sid_start</xr-xml-map>
            <xr-task>basic-services</xr-task>
            <xr-bag-primitive-type>uint32_t</xr-bag-primitive-type>
            <xr-bag-version>1 1</xr-bag-version>
            <type>
              <type-name>uint32</type-name>
            </type>
          </sid-start>
          <sid-count config="false" is-key="false" is-yang-key="false" node="leaf">
            <xr-path>/oper/srms/gl/active/sid/ipv6/&lt;srms_oper_MappingMi_IP&gt;,&lt;srms_oper_MappingMi_Prefix&gt;~srms_mi_t_b.sid_count</xr-path>
            <xr-xml-map>srms_show:sid_count</xr-xml-map>
            <xr-task>basic-services</xr-task>
            <xr-bag-primitive-type>uint32_t</xr-bag-primitive-type>
            <xr-bag-version>1 1</xr-bag-version>
            <type>
              <type-name>uint32</type-name>
            </type>
          </sid-count>
          <last-prefix config="false" is-key="false" is-yang-key="false" node="leaf">
            <xr-path>/oper/srms/gl/active/sid/ipv6/&lt;srms_oper_MappingMi_IP&gt;,&lt;srms_oper_MappingMi_Prefix&gt;~srms_mi_t_b.last_prefix</xr-path>
            <xr-xml-map>srms_show:last_prefix</xr-xml-map>
            <xr-task>basic-services</xr-task>
            <xr-bag-primitive-type>string</xr-bag-primitive-type>
            <xr-bag-version>1 1</xr-bag-version>
            <type length="0..50">
              <type-name>string</type-name>
            </type>
          </last-prefix>
          <last-sid-index config="false" is-key="false" is-yang-key="false" node="leaf">
            <xr-path>/oper/srms/gl/active/sid/ipv6/&lt;srms_oper_MappingMi_IP&gt;,&lt;srms_oper_MappingMi_Prefix&gt;~srms_mi_t_b.last_sid_index</xr-path>
            <xr-xml-map>srms_show:last_sid_index</xr-xml-map>
            <xr-task>basic-services</xr-task>
            <xr-bag-primitive-type>uint32_t</xr-bag-primitive-type>
            <xr-bag-version>1 1</xr-bag-version>
            <type>
              <type-name>uint32</type-name>
            </type>
          </last-sid-index>
          <flag-attached config="false" is-key="false" is-yang-key="false" node="leaf">
            <xr-path>/oper/srms/gl/active/sid/ipv6/&lt;srms_oper_MappingMi_IP&gt;,&lt;srms_oper_MappingMi_Prefix&gt;~srms_mi_t_b.flag_attached</xr-path>
            <xr-xml-map>srms_show:flag_attached</xr-xml-map>
            <xr-task>basic-services</xr-task>
            <xr-bag-primitive-type>int</xr-bag-primitive-type>
            <xr-bag-version>1 1</xr-bag-version>
            <type>
              <type-name>Srms-mi-flag-e-b</type-name>
            </type>
          </flag-attached>
        </mapping-mi>
      </mapping-ipv6>
    </mapping>
    <adjacency-sid config="false" is-key="false" node="container" presence="false">
      <xr-path>/oper/srms/gl/active/adjacency_sid/</xr-path>
      <xr-xml-map>srms_oper:AdjacencySID</xr-xml-map>
      <xr-task>basic-services</xr-task>
      <l2-adjacency config="false" is-key="false" node="container" presence="false">
        <xr-path>/oper/srms/gl/active/adjacency_sid/l2_adjacency/</xr-path>
        <xr-xml-map>srms_oper:L2Adjacency</xr-xml-map>
        <xr-task>basic-services</xr-task>
        <interfaces config="false" is-key="false" node="container" presence="false">
          <xr-path>/oper/srms/gl/active/adjacency_sid/l2_adjacency/intf/</xr-path>
          <xr-xml-map>srms_oper:InterfaceTable</xr-xml-map>
          <xr-task>basic-services</xr-task>
          <interface config="false" key="interface-name" node="list">
            <xr-path>/oper/srms/gl/active/adjacency_sid/l2_adjacency/intf/&lt;srms_oper_Interface_Interface&gt;/</xr-path>
            <xr-xml-map>srms_oper:Interface</xr-xml-map>
            <xr-task>basic-services</xr-task>
            <address-family config="false" is-key="false" node="container" presence="false">
              <xr-path>/oper/srms/gl/active/adjacency_sid/l2_adjacency/intf/&lt;srms_oper_Interface_Interface&gt;/afi/</xr-path>
              <xr-xml-map>srms_oper:AddressFamily</xr-xml-map>
              <xr-task>basic-services</xr-task>
              <ipv4 config="false" is-key="false" node="container" presence="false">
                <xr-path>/oper/srms/gl/active/adjacency_sid/l2_adjacency/intf/&lt;srms_oper_Interface_Interface&gt;/afi/ipv4/</xr-path>
                <xr-xml-map>srms_oper:IPv4</xr-xml-map>
                <xr-task>basic-services</xr-task>
                <sid-record config="false" node="list">
                  <xr-path>/oper/srms/gl/active/adjacency_sid/l2_adjacency/intf/&lt;srms_oper_Interface_Interface&gt;/afi/ipv4/&lt;srms_oper_SIDRecord_SIDType&gt;,&lt;srms_oper_SIDRecord_SIDValue&gt;</xr-path>
                  <xr-xml-map>srms_oper:SIDRecord</xr-xml-map>
                  <xr-task>basic-services</xr-task>
                  <xr-bag-grp-name>srms_l2_adj_t_b</xr-bag-grp-name>
                  <xr-bag>srms_show_l2adj.bag</xr-bag>
                  <sid-type config="false" is-key="true" is-yang-key="false" node="leaf">
                    <xr-pathformat>hex_nozerox</xr-pathformat>
                    <xr-primitive-type>uint32</xr-primitive-type>
                    <xr-path>/oper/srms/gl/active/adjacency_sid/l2_adjacency/intf/&lt;srms_oper_Interface_Interface&gt;/afi/ipv4/&lt;srms_oper_SIDRecord_SIDType&gt;,&lt;srms_oper_SIDRecord_SIDValue&gt;</xr-path>
                    <xr-xml-map>srms_oper:SIDType</xr-xml-map>
                    <xr-task>basic-services</xr-task>
                    <xr-sch-type>Enum</xr-sch-type>
                    <xr-sch-arg-name>&lt;srms_oper_SIDRecord_SIDType&gt;</xr-sch-arg-name>
                    <type>
                      <type-name>Sid-type-enum</type-name>
                    </type>
                  </sid-type>
                  <sid-value config="false" is-key="true" is-yang-key="false" node="leaf">
                    <xr-pathformat>hex_nozerox</xr-pathformat>
                    <xr-primitive-type>uint32</xr-primitive-type>
                    <xr-path>/oper/srms/gl/active/adjacency_sid/l2_adjacency/intf/&lt;srms_oper_Interface_Interface&gt;/afi/ipv4/&lt;srms_oper_SIDRecord_SIDType&gt;,&lt;srms_oper_SIDRecord_SIDValue&gt;</xr-path>
                    <xr-xml-map>srms_oper:SIDValue</xr-xml-map>
                    <xr-task>basic-services</xr-task>
                    <xr-sch-type>Integer</xr-sch-type>
                    <xr-sch-arg-name>&lt;srms_oper_SIDRecord_SIDValue&gt;</xr-sch-arg-name>
                    <type>
                      <type-name>uint32</type-name>
                    </type>
                  </sid-value>
                  <nexthop-address config="false" is-key="false" node="container" presence="false">
                    <xr-path>/oper/srms/gl/active/adjacency_sid/l2_adjacency/intf/&lt;srms_oper_Interface_Interface&gt;/afi/ipv4/&lt;srms_oper_SIDRecord_SIDType&gt;,&lt;srms_oper_SIDRecord_SIDValue&gt;~srms_l2_adj_t_b.NexthopAddress</xr-path>
                    <xr-task>basic-services</xr-task>
                    <xr-bag-version>1 1</xr-bag-version>
                    <af config="false" is-key="false" is-yang-key="false" node="leaf">
                      <xr-path>/oper/srms/gl/active/adjacency_sid/l2_adjacency/intf/&lt;srms_oper_Interface_Interface&gt;/afi/ipv4/&lt;srms_oper_SIDRecord_SIDType&gt;,&lt;srms_oper_SIDRecord_SIDValue&gt;~srms_l2_adj_t_b.NexthopAddress.AF</xr-path>
                      <xr-xml-map>srms_show_l2adj:AF</xr-xml-map>
                      <xr-task>basic-services</xr-task>
                      <xr-bag-primitive-type>int</xr-bag-primitive-type>
                      <xr-bag-version>1 1</xr-bag-version>
                      <type>
                        <type-name>Srms-af</type-name>
                      </type>
                    </af>
                    <ipv4 config="false" is-key="false" is-yang-key="false" node="leaf">
                      <xr-path>/oper/srms/gl/active/adjacency_sid/l2_adjacency/intf/&lt;srms_oper_Interface_Interface&gt;/afi/ipv4/&lt;srms_oper_SIDRecord_SIDType&gt;,&lt;srms_oper_SIDRecord_SIDValue&gt;~srms_l2_adj_t_b.NexthopAddress.IPv4</xr-path>
                      <xr-xml-map>srms_show_l2adj:IPv4</xr-xml-map>
                      <xr-task>basic-services</xr-task>
                      <xr-bag-primitive-type>in_addr_t</xr-bag-primitive-type>
                      <xr-bag-version>1 1</xr-bag-version>
                      <when>../af = 'ipv4'</when>
                      <type>
                        <type-name>inet:ipv4-address</type-name>
                      </type>
                    </ipv4>
                    <ipv6 config="false" is-key="false" is-yang-key="false" node="leaf">
                      <xr-path>/oper/srms/gl/active/adjacency_sid/l2_adjacency/intf/&lt;srms_oper_Interface_Interface&gt;/afi/ipv4/&lt;srms_oper_SIDRecord_SIDType&gt;,&lt;srms_oper_SIDRecord_SIDValue&gt;~srms_l2_adj_t_b.NexthopAddress.IPv6</xr-path>
                      <xr-xml-map>srms_show_l2adj:IPv6</xr-xml-map>
                      <xr-task>basic-services</xr-task>
                      <xr-bag-primitive-type>in6_addr_t</xr-bag-primitive-type>
                      <xr-bag-version>1 1</xr-bag-version>
                      <when>../af = 'ipv6'</when>
                      <type>
                        <type-name>In6-addr-t-b</type-name>
                      </type>
                    </ipv6>
                  </nexthop-address>
                  <interface-name config="false" is-key="false" is-yang-key="false" node="leaf">
                    <xr-path>/oper/srms/gl/active/adjacency_sid/l2_adjacency/intf/&lt;srms_oper_Interface_Interface&gt;/afi/ipv4/&lt;srms_oper_SIDRecord_SIDType&gt;,&lt;srms_oper_SIDRecord_SIDValue&gt;~srms_l2_adj_t_b.InterfaceName</xr-path>
                    <xr-xml-map>srms_show_l2adj:InterfaceName</xr-xml-map>
                    <xr-task>basic-services</xr-task>
                    <xr-bag-primitive-type>string</xr-bag-primitive-type>
                    <xr-bag-version>1 1</xr-bag-version>
                    <type length="0..64">
                      <type-name>string</type-name>
                    </type>
                  </interface-name>
                  <sid-value-xr config="false" is-key="false" is-yang-key="false" node="leaf">
                    <xr-path>/oper/srms/gl/active/adjacency_sid/l2_adjacency/intf/&lt;srms_oper_Interface_Interface&gt;/afi/ipv4/&lt;srms_oper_SIDRecord_SIDType&gt;,&lt;srms_oper_SIDRecord_SIDValue&gt;~srms_l2_adj_t_b.SIDValue</xr-path>
                    <xr-xml-map>srms_show_l2adj:sid-value-xr</xr-xml-map>
                    <xr-task>basic-services</xr-task>
                    <xr-bag-primitive-type>uint32_t</xr-bag-primitive-type>
                    <xr-bag-version>1 1</xr-bag-version>
                    <type>
                      <type-name>uint32</type-name>
                    </type>
                  </sid-value-xr>
                  <sid-type-xr config="false" is-key="false" is-yang-key="false" node="leaf">
                    <xr-path>/oper/srms/gl/active/adjacency_sid/l2_adjacency/intf/&lt;srms_oper_Interface_Interface&gt;/afi/ipv4/&lt;srms_oper_SIDRecord_SIDType&gt;,&lt;srms_oper_SIDRecord_SIDValue&gt;~srms_l2_adj_t_b.SIDType</xr-path>
                    <xr-xml-map>srms_show_l2adj:sid-type-xr</xr-xml-map>
                    <xr-task>basic-services</xr-task>
                    <xr-bag-primitive-type>uint32_t</xr-bag-primitive-type>
                    <xr-bag-version>1 1</xr-bag-version>
                    <type>
                      <type-name>uint32</type-name>
                    </type>
                  </sid-type-xr>
                  <address-family config="false" is-key="false" is-yang-key="false" node="leaf">
                    <xr-path>/oper/srms/gl/active/adjacency_sid/l2_adjacency/intf/&lt;srms_oper_Interface_Interface&gt;/afi/ipv4/&lt;srms_oper_SIDRecord_SIDType&gt;,&lt;srms_oper_SIDRecord_SIDValue&gt;~srms_l2_adj_t_b.AddressFamily</xr-path>
                    <xr-xml-map>srms_show_l2adj:AddressFamily</xr-xml-map>
                    <xr-task>basic-services</xr-task>
                    <xr-bag-primitive-type>uint32_t</xr-bag-primitive-type>
                    <xr-bag-version>1 1</xr-bag-version>
                    <type>
                      <type-name>uint32</type-name>
                    </type>
                  </address-family>
                  <has-nexthop config="false" is-key="false" is-yang-key="false" node="leaf">
                    <xr-path>/oper/srms/gl/active/adjacency_sid/l2_adjacency/intf/&lt;srms_oper_Interface_Interface&gt;/afi/ipv4/&lt;srms_oper_SIDRecord_SIDType&gt;,&lt;srms_oper_SIDRecord_SIDValue&gt;~srms_l2_adj_t_b.HasNexthop</xr-path>
                    <xr-xml-map>srms_show_l2adj:HasNexthop</xr-xml-map>
                    <xr-task>basic-services</xr-task>
                    <xr-bag-primitive-type>bool</xr-bag-primitive-type>
                    <xr-bag-version>1 1</xr-bag-version>
                    <type>
                      <type-name>boolean</type-name>
                    </type>
                  </has-nexthop>
                  <interface-count config="false" is-key="false" is-yang-key="false" node="leaf">
                    <xr-path>/oper/srms/gl/active/adjacency_sid/l2_adjacency/intf/&lt;srms_oper_Interface_Interface&gt;/afi/ipv4/&lt;srms_oper_SIDRecord_SIDType&gt;,&lt;srms_oper_SIDRecord_SIDValue&gt;~srms_l2_adj_t_b.InterfaceCount</xr-path>
                    <xr-xml-map>srms_show_l2adj:InterfaceCount</xr-xml-map>
                    <xr-task>basic-services</xr-task>
                    <xr-bag-primitive-type>int32_t</xr-bag-primitive-type>
                    <xr-bag-version>1 1</xr-bag-version>
                    <type>
                      <type-name>int32</type-name>
                    </type>
                  </interface-count>
                  <interface-delete-count config="false" is-key="false" is-yang-key="false" node="leaf">
                    <xr-path>/oper/srms/gl/active/adjacency_sid/l2_adjacency/intf/&lt;srms_oper_Interface_Interface&gt;/afi/ipv4/&lt;srms_oper_SIDRecord_SIDType&gt;,&lt;srms_oper_SIDRecord_SIDValue&gt;~srms_l2_adj_t_b.InterfaceDeleteCount</xr-path>
                    <xr-xml-map>srms_show_l2adj:InterfaceDeleteCount</xr-xml-map>
                    <xr-task>basic-services</xr-task>
                    <xr-bag-primitive-type>int32_t</xr-bag-primitive-type>
                    <xr-bag-version>1 1</xr-bag-version>
                    <type>
                      <type-name>int32</type-name>
                    </type>
                  </interface-delete-count>
                </sid-record>
              </ipv4>
              <ipv6 config="false" is-key="false" node="container" presence="false">
                <xr-path>/oper/srms/gl/active/adjacency_sid/l2_adjacency/intf/&lt;srms_oper_Interface_Interface&gt;/afi/ipv6/</xr-path>
                <xr-xml-map>srms_oper:IPv6</xr-xml-map>
                <xr-task>basic-services</xr-task>
                <sid-record config="false" node="list">
                  <xr-path>/oper/srms/gl/active/adjacency_sid/l2_adjacency/intf/&lt;srms_oper_Interface_Interface&gt;/afi/ipv6/&lt;srms_oper_SIDRecord_SIDType&gt;,&lt;srms_oper_SIDRecord_SIDValue&gt;</xr-path>
                  <xr-xml-map>srms_oper:SIDRecord</xr-xml-map>
                  <xr-task>basic-services</xr-task>
                  <xr-bag-grp-name>srms_l2_adj_t_b</xr-bag-grp-name>
                  <xr-bag>srms_show_l2adj.bag</xr-bag>
                  <sid-type config="false" is-key="true" is-yang-key="false" node="leaf">
                    <xr-pathformat>hex_nozerox</xr-pathformat>
                    <xr-primitive-type>uint32</xr-primitive-type>
                    <xr-path>/oper/srms/gl/active/adjacency_sid/l2_adjacency/intf/&lt;srms_oper_Interface_Interface&gt;/afi/ipv6/&lt;srms_oper_SIDRecord_SIDType&gt;,&lt;srms_oper_SIDRecord_SIDValue&gt;</xr-path>
                    <xr-xml-map>srms_oper:SIDType</xr-xml-map>
                    <xr-task>basic-services</xr-task>
                    <xr-sch-type>Enum</xr-sch-type>
                    <xr-sch-arg-name>&lt;srms_oper_SIDRecord_SIDType&gt;</xr-sch-arg-name>
                    <type>
                      <type-name>Sid-type-enum</type-name>
                    </type>
                  </sid-type>
                  <sid-value config="false" is-key="true" is-yang-key="false" node="leaf">
                    <xr-pathformat>hex_nozerox</xr-pathformat>
                    <xr-primitive-type>uint32</xr-primitive-type>
                    <xr-path>/oper/srms/gl/active/adjacency_sid/l2_adjacency/intf/&lt;srms_oper_Interface_Interface&gt;/afi/ipv6/&lt;srms_oper_SIDRecord_SIDType&gt;,&lt;srms_oper_SIDRecord_SIDValue&gt;</xr-path>
                    <xr-xml-map>srms_oper:SIDValue</xr-xml-map>
                    <xr-task>basic-services</xr-task>
                    <xr-sch-type>Integer</xr-sch-type>
                    <xr-sch-arg-name>&lt;srms_oper_SIDRecord_SIDValue&gt;</xr-sch-arg-name>
                    <type>
                      <type-name>uint32</type-name>
                    </type>
                  </sid-value>
                  <nexthop-address config="false" is-key="false" node="container" presence="false">
                    <xr-path>/oper/srms/gl/active/adjacency_sid/l2_adjacency/intf/&lt;srms_oper_Interface_Interface&gt;/afi/ipv6/&lt;srms_oper_SIDRecord_SIDType&gt;,&lt;srms_oper_SIDRecord_SIDValue&gt;~srms_l2_adj_t_b.NexthopAddress</xr-path>
                    <xr-task>basic-services</xr-task>
                    <xr-bag-version>1 1</xr-bag-version>
                    <af config="false" is-key="false" is-yang-key="false" node="leaf">
                      <xr-path>/oper/srms/gl/active/adjacency_sid/l2_adjacency/intf/&lt;srms_oper_Interface_Interface&gt;/afi/ipv6/&lt;srms_oper_SIDRecord_SIDType&gt;,&lt;srms_oper_SIDRecord_SIDValue&gt;~srms_l2_adj_t_b.NexthopAddress.AF</xr-path>
                      <xr-xml-map>srms_show_l2adj:AF</xr-xml-map>
                      <xr-task>basic-services</xr-task>
                      <xr-bag-primitive-type>int</xr-bag-primitive-type>
                      <xr-bag-version>1 1</xr-bag-version>
                      <type>
                        <type-name>Srms-af</type-name>
                      </type>
                    </af>
                    <ipv4 config="false" is-key="false" is-yang-key="false" node="leaf">
                      <xr-path>/oper/srms/gl/active/adjacency_sid/l2_adjacency/intf/&lt;srms_oper_Interface_Interface&gt;/afi/ipv6/&lt;srms_oper_SIDRecord_SIDType&gt;,&lt;srms_oper_SIDRecord_SIDValue&gt;~srms_l2_adj_t_b.NexthopAddress.IPv4</xr-path>
                      <xr-xml-map>srms_show_l2adj:IPv4</xr-xml-map>
                      <xr-task>basic-services</xr-task>
                      <xr-bag-primitive-type>in_addr_t</xr-bag-primitive-type>
                      <xr-bag-version>1 1</xr-bag-version>
                      <when>../af = 'ipv4'</when>
                      <type>
                        <type-name>inet:ipv4-address</type-name>
                      </type>
                    </ipv4>
                    <ipv6 config="false" is-key="false" is-yang-key="false" node="leaf">
                      <xr-path>/oper/srms/gl/active/adjacency_sid/l2_adjacency/intf/&lt;srms_oper_Interface_Interface&gt;/afi/ipv6/&lt;srms_oper_SIDRecord_SIDType&gt;,&lt;srms_oper_SIDRecord_SIDValue&gt;~srms_l2_adj_t_b.NexthopAddress.IPv6</xr-path>
                      <xr-xml-map>srms_show_l2adj:IPv6</xr-xml-map>
                      <xr-task>basic-services</xr-task>
                      <xr-bag-primitive-type>in6_addr_t</xr-bag-primitive-type>
                      <xr-bag-version>1 1</xr-bag-version>
                      <when>../af = 'ipv6'</when>
                      <type>
                        <type-name>In6-addr-t-b</type-name>
                      </type>
                    </ipv6>
                  </nexthop-address>
                  <interface-name config="false" is-key="false" is-yang-key="false" node="leaf">
                    <xr-path>/oper/srms/gl/active/adjacency_sid/l2_adjacency/intf/&lt;srms_oper_Interface_Interface&gt;/afi/ipv6/&lt;srms_oper_SIDRecord_SIDType&gt;,&lt;srms_oper_SIDRecord_SIDValue&gt;~srms_l2_adj_t_b.InterfaceName</xr-path>
                    <xr-xml-map>srms_show_l2adj:InterfaceName</xr-xml-map>
                    <xr-task>basic-services</xr-task>
                    <xr-bag-primitive-type>string</xr-bag-primitive-type>
                    <xr-bag-version>1 1</xr-bag-version>
                    <type length="0..64">
                      <type-name>string</type-name>
                    </type>
                  </interface-name>
                  <sid-value-xr config="false" is-key="false" is-yang-key="false" node="leaf">
                    <xr-path>/oper/srms/gl/active/adjacency_sid/l2_adjacency/intf/&lt;srms_oper_Interface_Interface&gt;/afi/ipv6/&lt;srms_oper_SIDRecord_SIDType&gt;,&lt;srms_oper_SIDRecord_SIDValue&gt;~srms_l2_adj_t_b.SIDValue</xr-path>
                    <xr-xml-map>srms_show_l2adj:sid-value-xr</xr-xml-map>
                    <xr-task>basic-services</xr-task>
                    <xr-bag-primitive-type>uint32_t</xr-bag-primitive-type>
                    <xr-bag-version>1 1</xr-bag-version>
                    <type>
                      <type-name>uint32</type-name>
                    </type>
                  </sid-value-xr>
                  <sid-type-xr config="false" is-key="false" is-yang-key="false" node="leaf">
                    <xr-path>/oper/srms/gl/active/adjacency_sid/l2_adjacency/intf/&lt;srms_oper_Interface_Interface&gt;/afi/ipv6/&lt;srms_oper_SIDRecord_SIDType&gt;,&lt;srms_oper_SIDRecord_SIDValue&gt;~srms_l2_adj_t_b.SIDType</xr-path>
                    <xr-xml-map>srms_show_l2adj:sid-type-xr</xr-xml-map>
                    <xr-task>basic-services</xr-task>
                    <xr-bag-primitive-type>uint32_t</xr-bag-primitive-type>
                    <xr-bag-version>1 1</xr-bag-version>
                    <type>
                      <type-name>uint32</type-name>
                    </type>
                  </sid-type-xr>
                  <address-family config="false" is-key="false" is-yang-key="false" node="leaf">
                    <xr-path>/oper/srms/gl/active/adjacency_sid/l2_adjacency/intf/&lt;srms_oper_Interface_Interface&gt;/afi/ipv6/&lt;srms_oper_SIDRecord_SIDType&gt;,&lt;srms_oper_SIDRecord_SIDValue&gt;~srms_l2_adj_t_b.AddressFamily</xr-path>
                    <xr-xml-map>srms_show_l2adj:AddressFamily</xr-xml-map>
                    <xr-task>basic-services</xr-task>
                    <xr-bag-primitive-type>uint32_t</xr-bag-primitive-type>
                    <xr-bag-version>1 1</xr-bag-version>
                    <type>
                      <type-name>uint32</type-name>
                    </type>
                  </address-family>
                  <has-nexthop config="false" is-key="false" is-yang-key="false" node="leaf">
                    <xr-path>/oper/srms/gl/active/adjacency_sid/l2_adjacency/intf/&lt;srms_oper_Interface_Interface&gt;/afi/ipv6/&lt;srms_oper_SIDRecord_SIDType&gt;,&lt;srms_oper_SIDRecord_SIDValue&gt;~srms_l2_adj_t_b.HasNexthop</xr-path>
                    <xr-xml-map>srms_show_l2adj:HasNexthop</xr-xml-map>
                    <xr-task>basic-services</xr-task>
                    <xr-bag-primitive-type>bool</xr-bag-primitive-type>
                    <xr-bag-version>1 1</xr-bag-version>
                    <type>
                      <type-name>boolean</type-name>
                    </type>
                  </has-nexthop>
                  <interface-count config="false" is-key="false" is-yang-key="false" node="leaf">
                    <xr-path>/oper/srms/gl/active/adjacency_sid/l2_adjacency/intf/&lt;srms_oper_Interface_Interface&gt;/afi/ipv6/&lt;srms_oper_SIDRecord_SIDType&gt;,&lt;srms_oper_SIDRecord_SIDValue&gt;~srms_l2_adj_t_b.InterfaceCount</xr-path>
                    <xr-xml-map>srms_show_l2adj:InterfaceCount</xr-xml-map>
                    <xr-task>basic-services</xr-task>
                    <xr-bag-primitive-type>int32_t</xr-bag-primitive-type>
                    <xr-bag-version>1 1</xr-bag-version>
                    <type>
                      <type-name>int32</type-name>
                    </type>
                  </interface-count>
                  <interface-delete-count config="false" is-key="false" is-yang-key="false" node="leaf">
                    <xr-path>/oper/srms/gl/active/adjacency_sid/l2_adjacency/intf/&lt;srms_oper_Interface_Interface&gt;/afi/ipv6/&lt;srms_oper_SIDRecord_SIDType&gt;,&lt;srms_oper_SIDRecord_SIDValue&gt;~srms_l2_adj_t_b.InterfaceDeleteCount</xr-path>
                    <xr-xml-map>srms_show_l2adj:InterfaceDeleteCount</xr-xml-map>
                    <xr-task>basic-services</xr-task>
                    <xr-bag-primitive-type>int32_t</xr-bag-primitive-type>
                    <xr-bag-version>1 1</xr-bag-version>
                    <type>
                      <type-name>int32</type-name>
                    </type>
                  </interface-delete-count>
                </sid-record>
              </ipv6>
            </address-family>
            <interface-name config="false" is-key="true" is-yang-key="true" node="leaf">
              <xr-data-handler>ignore</xr-data-handler>
              <xr-primitive-type>string</xr-primitive-type>
              <xr-path>/oper/srms/gl/active/adjacency_sid/l2_adjacency/intf/&lt;srms_oper_Interface_Interface&gt;/</xr-path>
              <xr-xml-map>srms_oper:InterfaceName</xr-xml-map>
              <xr-task>basic-services</xr-task>
              <xr-sch-type>InterfaceName</xr-sch-type>
              <xr-sch-arg-name>&lt;srms_oper_Interface_Interface&gt;</xr-sch-arg-name>
              <type>
                <type-name>xr:Interface-name</type-name>
              </type>
            </interface-name>
          </interface>
        </interfaces>
      </l2-adjacency>
    </adjacency-sid>
    <policy config="false" is-key="false" node="container" presence="false">
      <xr-path>/oper/srms/gl/active/policy/</xr-path>
      <xr-xml-map>srms_oper:Policy</xr-xml-map>
      <xr-task>basic-services</xr-task>
      <policy-ipv4 config="false" is-key="false" node="container" presence="false">
        <xr-path>/oper/srms/gl/active/policy/ipv4/</xr-path>
        <xr-xml-map>srms_oper:PolicyIpv4</xr-xml-map>
        <xr-task>basic-services</xr-task>
        <policy-ipv4-backup config="false" is-key="false" node="container" presence="false">
          <xr-path>/oper/srms/gl/active/policy/ipv4/backup/</xr-path>
          <xr-xml-map>srms_oper:PolicyIpv4Backup</xr-xml-map>
          <xr-task>basic-services</xr-task>
          <policy-mi config="false" key="mi-id" node="list">
            <xr-path>/oper/srms/gl/active/policy/ipv4/backup/&lt;srms_oper_PolicyMi_mi_id&gt;</xr-path>
            <xr-xml-map>srms_oper:PolicyMi</xr-xml-map>
            <xr-task>basic-services</xr-task>
            <xr-bag-grp-name>srms_mi_t_b</xr-bag-grp-name>
            <xr-bag>srms_show.bag</xr-bag>
            <mi-id config="false" is-key="true" is-yang-key="true" node="leaf">
              <xr-data-handler>ignore</xr-data-handler>
              <xr-primitive-type>string</xr-primitive-type>
              <xr-path>/oper/srms/gl/active/policy/ipv4/backup/&lt;srms_oper_PolicyMi_mi_id&gt;</xr-path>
              <xr-xml-map>srms_oper:MiId</xr-xml-map>
              <xr-task>basic-services</xr-task>
              <xr-sch-type>String</xr-sch-type>
              <xr-sch-arg-name>&lt;srms_oper_PolicyMi_mi_id&gt;</xr-sch-arg-name>
              <type>
                <type-name>xr:Cisco-ios-xr-string</type-name>
              </type>
            </mi-id>
            <addr config="false" is-key="false" node="container" presence="false">
              <xr-path>/oper/srms/gl/active/policy/ipv4/backup/&lt;srms_oper_PolicyMi_mi_id&gt;~srms_mi_t_b.addr</xr-path>
              <xr-task>basic-services</xr-task>
              <xr-bag-version>1 1</xr-bag-version>
              <af config="false" is-key="false" is-yang-key="false" node="leaf">
                <xr-path>/oper/srms/gl/active/policy/ipv4/backup/&lt;srms_oper_PolicyMi_mi_id&gt;~srms_mi_t_b.addr.AF</xr-path>
                <xr-xml-map>srms_show:AF</xr-xml-map>
                <xr-task>basic-services</xr-task>
                <xr-bag-primitive-type>int</xr-bag-primitive-type>
                <xr-bag-version>1 1</xr-bag-version>
                <type>
                  <type-name>Srms-mi-af-e-b</type-name>
                </type>
              </af>
              <ipv4 config="false" is-key="false" is-yang-key="false" node="leaf">
                <xr-path>/oper/srms/gl/active/policy/ipv4/backup/&lt;srms_oper_PolicyMi_mi_id&gt;~srms_mi_t_b.addr.IPv4</xr-path>
                <xr-xml-map>srms_show:IPv4</xr-xml-map>
                <xr-task>basic-services</xr-task>
                <xr-bag-primitive-type>in_addr_t</xr-bag-primitive-type>
                <xr-bag-version>1 1</xr-bag-version>
                <when>../af = 'ipv4'</when>
                <type>
                  <type-name>inet:ipv4-address</type-name>
                </type>
              </ipv4>
              <ipv6 config="false" is-key="false" is-yang-key="false" node="leaf">
                <xr-path>/oper/srms/gl/active/policy/ipv4/backup/&lt;srms_oper_PolicyMi_mi_id&gt;~srms_mi_t_b.addr.IPv6</xr-path>
                <xr-xml-map>srms_show:IPv6</xr-xml-map>
                <xr-task>basic-services</xr-task>
                <xr-bag-primitive-type>in6_addr_t</xr-bag-primitive-type>
                <xr-bag-version>1 1</xr-bag-version>
                <when>../af = 'ipv6'</when>
                <type>
                  <type-name>In6-addr-t-b</type-name>
                </type>
              </ipv6>
            </addr>
            <src config="false" is-key="false" is-yang-key="false" node="leaf">
              <xr-path>/oper/srms/gl/active/policy/ipv4/backup/&lt;srms_oper_PolicyMi_mi_id&gt;~srms_mi_t_b.src</xr-path>
              <xr-xml-map>srms_show:src</xr-xml-map>
              <xr-task>basic-services</xr-task>
              <xr-bag-primitive-type>int</xr-bag-primitive-type>
              <xr-bag-version>1 1</xr-bag-version>
              <type>
                <type-name>Srms-mi-src-e-b</type-name>
              </type>
            </src>
            <router config="false" is-key="false" is-yang-key="false" node="leaf">
              <xr-path>/oper/srms/gl/active/policy/ipv4/backup/&lt;srms_oper_PolicyMi_mi_id&gt;~srms_mi_t_b.router</xr-path>
              <xr-xml-map>srms_show:router</xr-xml-map>
              <xr-task>basic-services</xr-task>
              <xr-bag-primitive-type>string</xr-bag-primitive-type>
              <xr-bag-version>1 1</xr-bag-version>
              <type length="0..30">
                <type-name>string</type-name>
              </type>
            </router>
            <area config="false" is-key="false" is-yang-key="false" node="leaf">
              <xr-path>/oper/srms/gl/active/policy/ipv4/backup/&lt;srms_oper_PolicyMi_mi_id&gt;~srms_mi_t_b.area</xr-path>
              <xr-xml-map>srms_show:area</xr-xml-map>
              <xr-task>basic-services</xr-task>
              <xr-bag-primitive-type>string</xr-bag-primitive-type>
              <xr-bag-version>1 1</xr-bag-version>
              <type length="0..30">
                <type-name>string</type-name>
              </type>
            </area>
            <prefix-xr config="false" is-key="false" is-yang-key="false" node="leaf">
              <xr-path>/oper/srms/gl/active/policy/ipv4/backup/&lt;srms_oper_PolicyMi_mi_id&gt;~srms_mi_t_b.prefix</xr-path>
              <xr-xml-map>srms_show:prefix-xr</xr-xml-map>
              <xr-task>basic-services</xr-task>
              <xr-bag-primitive-type>uint8_t</xr-bag-primitive-type>
              <xr-bag-version>1 1</xr-bag-version>
              <type>
                <type-name>uint8</type-name>
              </type>
            </prefix-xr>
            <sid-start config="false" is-key="false" is-yang-key="false" node="leaf">
              <xr-path>/oper/srms/gl/active/policy/ipv4/backup/&lt;srms_oper_PolicyMi_mi_id&gt;~srms_mi_t_b.sid_start</xr-path>
              <xr-xml-map>srms_show:sid_start</xr-xml-map>
              <xr-task>basic-services</xr-task>
              <xr-bag-primitive-type>uint32_t</xr-bag-primitive-type>
              <xr-bag-version>1 1</xr-bag-version>
              <type>
                <type-name>uint32</type-name>
              </type>
            </sid-start>
            <sid-count config="false" is-key="false" is-yang-key="false" node="leaf">
              <xr-path>/oper/srms/gl/active/policy/ipv4/backup/&lt;srms_oper_PolicyMi_mi_id&gt;~srms_mi_t_b.sid_count</xr-path>
              <xr-xml-map>srms_show:sid_count</xr-xml-map>
              <xr-task>basic-services</xr-task>
              <xr-bag-primitive-type>uint32_t</xr-bag-primitive-type>
              <xr-bag-version>1 1</xr-bag-version>
              <type>
                <type-name>uint32</type-name>
              </type>
            </sid-count>
            <last-prefix config="false" is-key="false" is-yang-key="false" node="leaf">
              <xr-path>/oper/srms/gl/active/policy/ipv4/backup/&lt;srms_oper_PolicyMi_mi_id&gt;~srms_mi_t_b.last_prefix</xr-path>
              <xr-xml-map>srms_show:last_prefix</xr-xml-map>
              <xr-task>basic-services</xr-task>
              <xr-bag-primitive-type>string</xr-bag-primitive-type>
              <xr-bag-version>1 1</xr-bag-version>
              <type length="0..50">
                <type-name>string</type-name>
              </type>
            </last-prefix>
            <last-sid-index config="false" is-key="false" is-yang-key="false" node="leaf">
              <xr-path>/oper/srms/gl/active/policy/ipv4/backup/&lt;srms_oper_PolicyMi_mi_id&gt;~srms_mi_t_b.last_sid_index</xr-path>
              <xr-xml-map>srms_show:last_sid_index</xr-xml-map>
              <xr-task>basic-services</xr-task>
              <xr-bag-primitive-type>uint32_t</xr-bag-primitive-type>
              <xr-bag-version>1 1</xr-bag-version>
              <type>
                <type-name>uint32</type-name>
              </type>
            </last-sid-index>
            <flag-attached config="false" is-key="false" is-yang-key="false" node="leaf">
              <xr-path>/oper/srms/gl/active/policy/ipv4/backup/&lt;srms_oper_PolicyMi_mi_id&gt;~srms_mi_t_b.flag_attached</xr-path>
              <xr-xml-map>srms_show:flag_attached</xr-xml-map>
              <xr-task>basic-services</xr-task>
              <xr-bag-primitive-type>int</xr-bag-primitive-type>
              <xr-bag-version>1 1</xr-bag-version>
              <type>
                <type-name>Srms-mi-flag-e-b</type-name>
              </type>
            </flag-attached>
          </policy-mi>
        </policy-ipv4-backup>
        <policy-ipv4-active config="false" is-key="false" node="container" presence="false">
          <xr-path>/oper/srms/gl/active/policy/ipv4/active/</xr-path>
          <xr-xml-map>srms_oper:PolicyIpv4Active</xr-xml-map>
          <xr-task>basic-services</xr-task>
          <policy-mi config="false" key="mi-id" node="list">
            <xr-path>/oper/srms/gl/active/policy/ipv4/active/&lt;srms_oper_PolicyMi_mi_id&gt;</xr-path>
            <xr-xml-map>srms_oper:PolicyMi</xr-xml-map>
            <xr-task>basic-services</xr-task>
            <xr-bag-grp-name>srms_mi_t_b</xr-bag-grp-name>
            <xr-bag>srms_show.bag</xr-bag>
            <mi-id config="false" is-key="true" is-yang-key="true" node="leaf">
              <xr-data-handler>ignore</xr-data-handler>
              <xr-primitive-type>string</xr-primitive-type>
              <xr-path>/oper/srms/gl/active/policy/ipv4/active/&lt;srms_oper_PolicyMi_mi_id&gt;</xr-path>
              <xr-xml-map>srms_oper:MiId</xr-xml-map>
              <xr-task>basic-services</xr-task>
              <xr-sch-type>String</xr-sch-type>
              <xr-sch-arg-name>&lt;srms_oper_PolicyMi_mi_id&gt;</xr-sch-arg-name>
              <type>
                <type-name>xr:Cisco-ios-xr-string</type-name>
              </type>
            </mi-id>
            <addr config="false" is-key="false" node="container" presence="false">
              <xr-path>/oper/srms/gl/active/policy/ipv4/active/&lt;srms_oper_PolicyMi_mi_id&gt;~srms_mi_t_b.addr</xr-path>
              <xr-task>basic-services</xr-task>
              <xr-bag-version>1 1</xr-bag-version>
              <af config="false" is-key="false" is-yang-key="false" node="leaf">
                <xr-path>/oper/srms/gl/active/policy/ipv4/active/&lt;srms_oper_PolicyMi_mi_id&gt;~srms_mi_t_b.addr.AF</xr-path>
                <xr-xml-map>srms_show:AF</xr-xml-map>
                <xr-task>basic-services</xr-task>
                <xr-bag-primitive-type>int</xr-bag-primitive-type>
                <xr-bag-version>1 1</xr-bag-version>
                <type>
                  <type-name>Srms-mi-af-e-b</type-name>
                </type>
              </af>
              <ipv4 config="false" is-key="false" is-yang-key="false" node="leaf">
                <xr-path>/oper/srms/gl/active/policy/ipv4/active/&lt;srms_oper_PolicyMi_mi_id&gt;~srms_mi_t_b.addr.IPv4</xr-path>
                <xr-xml-map>srms_show:IPv4</xr-xml-map>
                <xr-task>basic-services</xr-task>
                <xr-bag-primitive-type>in_addr_t</xr-bag-primitive-type>
                <xr-bag-version>1 1</xr-bag-version>
                <when>../af = 'ipv4'</when>
                <type>
                  <type-name>inet:ipv4-address</type-name>
                </type>
              </ipv4>
              <ipv6 config="false" is-key="false" is-yang-key="false" node="leaf">
                <xr-path>/oper/srms/gl/active/policy/ipv4/active/&lt;srms_oper_PolicyMi_mi_id&gt;~srms_mi_t_b.addr.IPv6</xr-path>
                <xr-xml-map>srms_show:IPv6</xr-xml-map>
                <xr-task>basic-services</xr-task>
                <xr-bag-primitive-type>in6_addr_t</xr-bag-primitive-type>
                <xr-bag-version>1 1</xr-bag-version>
                <when>../af = 'ipv6'</when>
                <type>
                  <type-name>In6-addr-t-b</type-name>
                </type>
              </ipv6>
            </addr>
            <src config="false" is-key="false" is-yang-key="false" node="leaf">
              <xr-path>/oper/srms/gl/active/policy/ipv4/active/&lt;srms_oper_PolicyMi_mi_id&gt;~srms_mi_t_b.src</xr-path>
              <xr-xml-map>srms_show:src</xr-xml-map>
              <xr-task>basic-services</xr-task>
              <xr-bag-primitive-type>int</xr-bag-primitive-type>
              <xr-bag-version>1 1</xr-bag-version>
              <type>
                <type-name>Srms-mi-src-e-b</type-name>
              </type>
            </src>
            <router config="false" is-key="false" is-yang-key="false" node="leaf">
              <xr-path>/oper/srms/gl/active/policy/ipv4/active/&lt;srms_oper_PolicyMi_mi_id&gt;~srms_mi_t_b.router</xr-path>
              <xr-xml-map>srms_show:router</xr-xml-map>
              <xr-task>basic-services</xr-task>
              <xr-bag-primitive-type>string</xr-bag-primitive-type>
              <xr-bag-version>1 1</xr-bag-version>
              <type length="0..30">
                <type-name>string</type-name>
              </type>
            </router>
            <area config="false" is-key="false" is-yang-key="false" node="leaf">
              <xr-path>/oper/srms/gl/active/policy/ipv4/active/&lt;srms_oper_PolicyMi_mi_id&gt;~srms_mi_t_b.area</xr-path>
              <xr-xml-map>srms_show:area</xr-xml-map>
              <xr-task>basic-services</xr-task>
              <xr-bag-primitive-type>string</xr-bag-primitive-type>
              <xr-bag-version>1 1</xr-bag-version>
              <type length="0..30">
                <type-name>string</type-name>
              </type>
            </area>
            <prefix-xr config="false" is-key="false" is-yang-key="false" node="leaf">
              <xr-path>/oper/srms/gl/active/policy/ipv4/active/&lt;srms_oper_PolicyMi_mi_id&gt;~srms_mi_t_b.prefix</xr-path>
              <xr-xml-map>srms_show:prefix-xr</xr-xml-map>
              <xr-task>basic-services</xr-task>
              <xr-bag-primitive-type>uint8_t</xr-bag-primitive-type>
              <xr-bag-version>1 1</xr-bag-version>
              <type>
                <type-name>uint8</type-name>
              </type>
            </prefix-xr>
            <sid-start config="false" is-key="false" is-yang-key="false" node="leaf">
              <xr-path>/oper/srms/gl/active/policy/ipv4/active/&lt;srms_oper_PolicyMi_mi_id&gt;~srms_mi_t_b.sid_start</xr-path>
              <xr-xml-map>srms_show:sid_start</xr-xml-map>
              <xr-task>basic-services</xr-task>
              <xr-bag-primitive-type>uint32_t</xr-bag-primitive-type>
              <xr-bag-version>1 1</xr-bag-version>
              <type>
                <type-name>uint32</type-name>
              </type>
            </sid-start>
            <sid-count config="false" is-key="false" is-yang-key="false" node="leaf">
              <xr-path>/oper/srms/gl/active/policy/ipv4/active/&lt;srms_oper_PolicyMi_mi_id&gt;~srms_mi_t_b.sid_count</xr-path>
              <xr-xml-map>srms_show:sid_count</xr-xml-map>
              <xr-task>basic-services</xr-task>
              <xr-bag-primitive-type>uint32_t</xr-bag-primitive-type>
              <xr-bag-version>1 1</xr-bag-version>
              <type>
                <type-name>uint32</type-name>
              </type>
            </sid-count>
            <last-prefix config="false" is-key="false" is-yang-key="false" node="leaf">
              <xr-path>/oper/srms/gl/active/policy/ipv4/active/&lt;srms_oper_PolicyMi_mi_id&gt;~srms_mi_t_b.last_prefix</xr-path>
              <xr-xml-map>srms_show:last_prefix</xr-xml-map>
              <xr-task>basic-services</xr-task>
              <xr-bag-primitive-type>string</xr-bag-primitive-type>
              <xr-bag-version>1 1</xr-bag-version>
              <type length="0..50">
                <type-name>string</type-name>
              </type>
            </last-prefix>
            <last-sid-index config="false" is-key="false" is-yang-key="false" node="leaf">
              <xr-path>/oper/srms/gl/active/policy/ipv4/active/&lt;srms_oper_PolicyMi_mi_id&gt;~srms_mi_t_b.last_sid_index</xr-path>
              <xr-xml-map>srms_show:last_sid_index</xr-xml-map>
              <xr-task>basic-services</xr-task>
              <xr-bag-primitive-type>uint32_t</xr-bag-primitive-type>
              <xr-bag-version>1 1</xr-bag-version>
              <type>
                <type-name>uint32</type-name>
              </type>
            </last-sid-index>
            <flag-attached config="false" is-key="false" is-yang-key="false" node="leaf">
              <xr-path>/oper/srms/gl/active/policy/ipv4/active/&lt;srms_oper_PolicyMi_mi_id&gt;~srms_mi_t_b.flag_attached</xr-path>
              <xr-xml-map>srms_show:flag_attached</xr-xml-map>
              <xr-task>basic-services</xr-task>
              <xr-bag-primitive-type>int</xr-bag-primitive-type>
              <xr-bag-version>1 1</xr-bag-version>
              <type>
                <type-name>Srms-mi-flag-e-b</type-name>
              </type>
            </flag-attached>
          </policy-mi>
        </policy-ipv4-active>
      </policy-ipv4>
      <policy-ipv6 config="false" is-key="false" node="container" presence="false">
        <xr-path>/oper/srms/gl/active/policy/ipv6/</xr-path>
        <xr-xml-map>srms_oper:PolicyIpv6</xr-xml-map>
        <xr-task>basic-services</xr-task>
        <policy-ipv6-backup config="false" is-key="false" node="container" presence="false">
          <xr-path>/oper/srms/gl/active/policy/ipv6/backup/</xr-path>
          <xr-xml-map>srms_oper:PolicyIpv6Backup</xr-xml-map>
          <xr-task>basic-services</xr-task>
          <policy-mi config="false" key="mi-id" node="list">
            <xr-path>/oper/srms/gl/active/policy/ipv6/backup/&lt;srms_oper_PolicyMi_mi_id&gt;</xr-path>
            <xr-xml-map>srms_oper:PolicyMi</xr-xml-map>
            <xr-task>basic-services</xr-task>
            <xr-bag-grp-name>srms_mi_t_b</xr-bag-grp-name>
            <xr-bag>srms_show.bag</xr-bag>
            <mi-id config="false" is-key="true" is-yang-key="true" node="leaf">
              <xr-data-handler>ignore</xr-data-handler>
              <xr-primitive-type>string</xr-primitive-type>
              <xr-path>/oper/srms/gl/active/policy/ipv6/backup/&lt;srms_oper_PolicyMi_mi_id&gt;</xr-path>
              <xr-xml-map>srms_oper:MiId</xr-xml-map>
              <xr-task>basic-services</xr-task>
              <xr-sch-type>String</xr-sch-type>
              <xr-sch-arg-name>&lt;srms_oper_PolicyMi_mi_id&gt;</xr-sch-arg-name>
              <type>
                <type-name>xr:Cisco-ios-xr-string</type-name>
              </type>
            </mi-id>
            <addr config="false" is-key="false" node="container" presence="false">
              <xr-path>/oper/srms/gl/active/policy/ipv6/backup/&lt;srms_oper_PolicyMi_mi_id&gt;~srms_mi_t_b.addr</xr-path>
              <xr-task>basic-services</xr-task>
              <xr-bag-version>1 1</xr-bag-version>
              <af config="false" is-key="false" is-yang-key="false" node="leaf">
                <xr-path>/oper/srms/gl/active/policy/ipv6/backup/&lt;srms_oper_PolicyMi_mi_id&gt;~srms_mi_t_b.addr.AF</xr-path>
                <xr-xml-map>srms_show:AF</xr-xml-map>
                <xr-task>basic-services</xr-task>
                <xr-bag-primitive-type>int</xr-bag-primitive-type>
                <xr-bag-version>1 1</xr-bag-version>
                <type>
                  <type-name>Srms-mi-af-e-b</type-name>
                </type>
              </af>
              <ipv4 config="false" is-key="false" is-yang-key="false" node="leaf">
                <xr-path>/oper/srms/gl/active/policy/ipv6/backup/&lt;srms_oper_PolicyMi_mi_id&gt;~srms_mi_t_b.addr.IPv4</xr-path>
                <xr-xml-map>srms_show:IPv4</xr-xml-map>
                <xr-task>basic-services</xr-task>
                <xr-bag-primitive-type>in_addr_t</xr-bag-primitive-type>
                <xr-bag-version>1 1</xr-bag-version>
                <when>../af = 'ipv4'</when>
                <type>
                  <type-name>inet:ipv4-address</type-name>
                </type>
              </ipv4>
              <ipv6 config="false" is-key="false" is-yang-key="false" node="leaf">
                <xr-path>/oper/srms/gl/active/policy/ipv6/backup/&lt;srms_oper_PolicyMi_mi_id&gt;~srms_mi_t_b.addr.IPv6</xr-path>
                <xr-xml-map>srms_show:IPv6</xr-xml-map>
                <xr-task>basic-services</xr-task>
                <xr-bag-primitive-type>in6_addr_t</xr-bag-primitive-type>
                <xr-bag-version>1 1</xr-bag-version>
                <when>../af = 'ipv6'</when>
                <type>
                  <type-name>In6-addr-t-b</type-name>
                </type>
              </ipv6>
            </addr>
            <src config="false" is-key="false" is-yang-key="false" node="leaf">
              <xr-path>/oper/srms/gl/active/policy/ipv6/backup/&lt;srms_oper_PolicyMi_mi_id&gt;~srms_mi_t_b.src</xr-path>
              <xr-xml-map>srms_show:src</xr-xml-map>
              <xr-task>basic-services</xr-task>
              <xr-bag-primitive-type>int</xr-bag-primitive-type>
              <xr-bag-version>1 1</xr-bag-version>
              <type>
                <type-name>Srms-mi-src-e-b</type-name>
              </type>
            </src>
            <router config="false" is-key="false" is-yang-key="false" node="leaf">
              <xr-path>/oper/srms/gl/active/policy/ipv6/backup/&lt;srms_oper_PolicyMi_mi_id&gt;~srms_mi_t_b.router</xr-path>
              <xr-xml-map>srms_show:router</xr-xml-map>
              <xr-task>basic-services</xr-task>
              <xr-bag-primitive-type>string</xr-bag-primitive-type>
              <xr-bag-version>1 1</xr-bag-version>
              <type length="0..30">
                <type-name>string</type-name>
              </type>
            </router>
            <area config="false" is-key="false" is-yang-key="false" node="leaf">
              <xr-path>/oper/srms/gl/active/policy/ipv6/backup/&lt;srms_oper_PolicyMi_mi_id&gt;~srms_mi_t_b.area</xr-path>
              <xr-xml-map>srms_show:area</xr-xml-map>
              <xr-task>basic-services</xr-task>
              <xr-bag-primitive-type>string</xr-bag-primitive-type>
              <xr-bag-version>1 1</xr-bag-version>
              <type length="0..30">
                <type-name>string</type-name>
              </type>
            </area>
            <prefix-xr config="false" is-key="false" is-yang-key="false" node="leaf">
              <xr-path>/oper/srms/gl/active/policy/ipv6/backup/&lt;srms_oper_PolicyMi_mi_id&gt;~srms_mi_t_b.prefix</xr-path>
              <xr-xml-map>srms_show:prefix-xr</xr-xml-map>
              <xr-task>basic-services</xr-task>
              <xr-bag-primitive-type>uint8_t</xr-bag-primitive-type>
              <xr-bag-version>1 1</xr-bag-version>
              <type>
                <type-name>uint8</type-name>
              </type>
            </prefix-xr>
            <sid-start config="false" is-key="false" is-yang-key="false" node="leaf">
              <xr-path>/oper/srms/gl/active/policy/ipv6/backup/&lt;srms_oper_PolicyMi_mi_id&gt;~srms_mi_t_b.sid_start</xr-path>
              <xr-xml-map>srms_show:sid_start</xr-xml-map>
              <xr-task>basic-services</xr-task>
              <xr-bag-primitive-type>uint32_t</xr-bag-primitive-type>
              <xr-bag-version>1 1</xr-bag-version>
              <type>
                <type-name>uint32</type-name>
              </type>
            </sid-start>
            <sid-count config="false" is-key="false" is-yang-key="false" node="leaf">
              <xr-path>/oper/srms/gl/active/policy/ipv6/backup/&lt;srms_oper_PolicyMi_mi_id&gt;~srms_mi_t_b.sid_count</xr-path>
              <xr-xml-map>srms_show:sid_count</xr-xml-map>
              <xr-task>basic-services</xr-task>
              <xr-bag-primitive-type>uint32_t</xr-bag-primitive-type>
              <xr-bag-version>1 1</xr-bag-version>
              <type>
                <type-name>uint32</type-name>
              </type>
            </sid-count>
            <last-prefix config="false" is-key="false" is-yang-key="false" node="leaf">
              <xr-path>/oper/srms/gl/active/policy/ipv6/backup/&lt;srms_oper_PolicyMi_mi_id&gt;~srms_mi_t_b.last_prefix</xr-path>
              <xr-xml-map>srms_show:last_prefix</xr-xml-map>
              <xr-task>basic-services</xr-task>
              <xr-bag-primitive-type>string</xr-bag-primitive-type>
              <xr-bag-version>1 1</xr-bag-version>
              <type length="0..50">
                <type-name>string</type-name>
              </type>
            </last-prefix>
            <last-sid-index config="false" is-key="false" is-yang-key="false" node="leaf">
              <xr-path>/oper/srms/gl/active/policy/ipv6/backup/&lt;srms_oper_PolicyMi_mi_id&gt;~srms_mi_t_b.last_sid_index</xr-path>
              <xr-xml-map>srms_show:last_sid_index</xr-xml-map>
              <xr-task>basic-services</xr-task>
              <xr-bag-primitive-type>uint32_t</xr-bag-primitive-type>
              <xr-bag-version>1 1</xr-bag-version>
              <type>
                <type-name>uint32</type-name>
              </type>
            </last-sid-index>
            <flag-attached config="false" is-key="false" is-yang-key="false" node="leaf">
              <xr-path>/oper/srms/gl/active/policy/ipv6/backup/&lt;srms_oper_PolicyMi_mi_id&gt;~srms_mi_t_b.flag_attached</xr-path>
              <xr-xml-map>srms_show:flag_attached</xr-xml-map>
              <xr-task>basic-services</xr-task>
              <xr-bag-primitive-type>int</xr-bag-primitive-type>
              <xr-bag-version>1 1</xr-bag-version>
              <type>
                <type-name>Srms-mi-flag-e-b</type-name>
              </type>
            </flag-attached>
          </policy-mi>
        </policy-ipv6-backup>
        <policy-ipv6-active config="false" is-key="false" node="container" presence="false">
          <xr-path>/oper/srms/gl/active/policy/ipv6/active/</xr-path>
          <xr-xml-map>srms_oper:PolicyIpv6Active</xr-xml-map>
          <xr-task>basic-services</xr-task>
          <policy-mi config="false" key="mi-id" node="list">
            <xr-path>/oper/srms/gl/active/policy/ipv6/active/&lt;srms_oper_PolicyMi_mi_id&gt;</xr-path>
            <xr-xml-map>srms_oper:PolicyMi</xr-xml-map>
            <xr-task>basic-services</xr-task>
            <xr-bag-grp-name>srms_mi_t_b</xr-bag-grp-name>
            <xr-bag>srms_show.bag</xr-bag>
            <mi-id config="false" is-key="true" is-yang-key="true" node="leaf">
              <xr-data-handler>ignore</xr-data-handler>
              <xr-primitive-type>string</xr-primitive-type>
              <xr-path>/oper/srms/gl/active/policy/ipv6/active/&lt;srms_oper_PolicyMi_mi_id&gt;</xr-path>
              <xr-xml-map>srms_oper:MiId</xr-xml-map>
              <xr-task>basic-services</xr-task>
              <xr-sch-type>String</xr-sch-type>
              <xr-sch-arg-name>&lt;srms_oper_PolicyMi_mi_id&gt;</xr-sch-arg-name>
              <type>
                <type-name>xr:Cisco-ios-xr-string</type-name>
              </type>
            </mi-id>
            <addr config="false" is-key="false" node="container" presence="false">
              <xr-path>/oper/srms/gl/active/policy/ipv6/active/&lt;srms_oper_PolicyMi_mi_id&gt;~srms_mi_t_b.addr</xr-path>
              <xr-task>basic-services</xr-task>
              <xr-bag-version>1 1</xr-bag-version>
              <af config="false" is-key="false" is-yang-key="false" node="leaf">
                <xr-path>/oper/srms/gl/active/policy/ipv6/active/&lt;srms_oper_PolicyMi_mi_id&gt;~srms_mi_t_b.addr.AF</xr-path>
                <xr-xml-map>srms_show:AF</xr-xml-map>
                <xr-task>basic-services</xr-task>
                <xr-bag-primitive-type>int</xr-bag-primitive-type>
                <xr-bag-version>1 1</xr-bag-version>
                <type>
                  <type-name>Srms-mi-af-e-b</type-name>
                </type>
              </af>
              <ipv4 config="false" is-key="false" is-yang-key="false" node="leaf">
                <xr-path>/oper/srms/gl/active/policy/ipv6/active/&lt;srms_oper_PolicyMi_mi_id&gt;~srms_mi_t_b.addr.IPv4</xr-path>
                <xr-xml-map>srms_show:IPv4</xr-xml-map>
                <xr-task>basic-services</xr-task>
                <xr-bag-primitive-type>in_addr_t</xr-bag-primitive-type>
                <xr-bag-version>1 1</xr-bag-version>
                <when>../af = 'ipv4'</when>
                <type>
                  <type-name>inet:ipv4-address</type-name>
                </type>
              </ipv4>
              <ipv6 config="false" is-key="false" is-yang-key="false" node="leaf">
                <xr-path>/oper/srms/gl/active/policy/ipv6/active/&lt;srms_oper_PolicyMi_mi_id&gt;~srms_mi_t_b.addr.IPv6</xr-path>
                <xr-xml-map>srms_show:IPv6</xr-xml-map>
                <xr-task>basic-services</xr-task>
                <xr-bag-primitive-type>in6_addr_t</xr-bag-primitive-type>
                <xr-bag-version>1 1</xr-bag-version>
                <when>../af = 'ipv6'</when>
                <type>
                  <type-name>In6-addr-t-b</type-name>
                </type>
              </ipv6>
            </addr>
            <src config="false" is-key="false" is-yang-key="false" node="leaf">
              <xr-path>/oper/srms/gl/active/policy/ipv6/active/&lt;srms_oper_PolicyMi_mi_id&gt;~srms_mi_t_b.src</xr-path>
              <xr-xml-map>srms_show:src</xr-xml-map>
              <xr-task>basic-services</xr-task>
              <xr-bag-primitive-type>int</xr-bag-primitive-type>
              <xr-bag-version>1 1</xr-bag-version>
              <type>
                <type-name>Srms-mi-src-e-b</type-name>
              </type>
            </src>
            <router config="false" is-key="false" is-yang-key="false" node="leaf">
              <xr-path>/oper/srms/gl/active/policy/ipv6/active/&lt;srms_oper_PolicyMi_mi_id&gt;~srms_mi_t_b.router</xr-path>
              <xr-xml-map>srms_show:router</xr-xml-map>
              <xr-task>basic-services</xr-task>
              <xr-bag-primitive-type>string</xr-bag-primitive-type>
              <xr-bag-version>1 1</xr-bag-version>
              <type length="0..30">
                <type-name>string</type-name>
              </type>
            </router>
            <area config="false" is-key="false" is-yang-key="false" node="leaf">
              <xr-path>/oper/srms/gl/active/policy/ipv6/active/&lt;srms_oper_PolicyMi_mi_id&gt;~srms_mi_t_b.area</xr-path>
              <xr-xml-map>srms_show:area</xr-xml-map>
              <xr-task>basic-services</xr-task>
              <xr-bag-primitive-type>string</xr-bag-primitive-type>
              <xr-bag-version>1 1</xr-bag-version>
              <type length="0..30">
                <type-name>string</type-name>
              </type>
            </area>
            <prefix-xr config="false" is-key="false" is-yang-key="false" node="leaf">
              <xr-path>/oper/srms/gl/active/policy/ipv6/active/&lt;srms_oper_PolicyMi_mi_id&gt;~srms_mi_t_b.prefix</xr-path>
              <xr-xml-map>srms_show:prefix-xr</xr-xml-map>
              <xr-task>basic-services</xr-task>
              <xr-bag-primitive-type>uint8_t</xr-bag-primitive-type>
              <xr-bag-version>1 1</xr-bag-version>
              <type>
                <type-name>uint8</type-name>
              </type>
            </prefix-xr>
            <sid-start config="false" is-key="false" is-yang-key="false" node="leaf">
              <xr-path>/oper/srms/gl/active/policy/ipv6/active/&lt;srms_oper_PolicyMi_mi_id&gt;~srms_mi_t_b.sid_start</xr-path>
              <xr-xml-map>srms_show:sid_start</xr-xml-map>
              <xr-task>basic-services</xr-task>
              <xr-bag-primitive-type>uint32_t</xr-bag-primitive-type>
              <xr-bag-version>1 1</xr-bag-version>
              <type>
                <type-name>uint32</type-name>
              </type>
            </sid-start>
            <sid-count config="false" is-key="false" is-yang-key="false" node="leaf">
              <xr-path>/oper/srms/gl/active/policy/ipv6/active/&lt;srms_oper_PolicyMi_mi_id&gt;~srms_mi_t_b.sid_count</xr-path>
              <xr-xml-map>srms_show:sid_count</xr-xml-map>
              <xr-task>basic-services</xr-task>
              <xr-bag-primitive-type>uint32_t</xr-bag-primitive-type>
              <xr-bag-version>1 1</xr-bag-version>
              <type>
                <type-name>uint32</type-name>
              </type>
            </sid-count>
            <last-prefix config="false" is-key="false" is-yang-key="false" node="leaf">
              <xr-path>/oper/srms/gl/active/policy/ipv6/active/&lt;srms_oper_PolicyMi_mi_id&gt;~srms_mi_t_b.last_prefix</xr-path>
              <xr-xml-map>srms_show:last_prefix</xr-xml-map>
              <xr-task>basic-services</xr-task>
              <xr-bag-primitive-type>string</xr-bag-primitive-type>
              <xr-bag-version>1 1</xr-bag-version>
              <type length="0..50">
                <type-name>string</type-name>
              </type>
            </last-prefix>
            <last-sid-index config="false" is-key="false" is-yang-key="false" node="leaf">
              <xr-path>/oper/srms/gl/active/policy/ipv6/active/&lt;srms_oper_PolicyMi_mi_id&gt;~srms_mi_t_b.last_sid_index</xr-path>
              <xr-xml-map>srms_show:last_sid_index</xr-xml-map>
              <xr-task>basic-services</xr-task>
              <xr-bag-primitive-type>uint32_t</xr-bag-primitive-type>
              <xr-bag-version>1 1</xr-bag-version>
              <type>
                <type-name>uint32</type-name>
              </type>
            </last-sid-index>
            <flag-attached config="false" is-key="false" is-yang-key="false" node="leaf">
              <xr-path>/oper/srms/gl/active/policy/ipv6/active/&lt;srms_oper_PolicyMi_mi_id&gt;~srms_mi_t_b.flag_attached</xr-path>
              <xr-xml-map>srms_show:flag_attached</xr-xml-map>
              <xr-task>basic-services</xr-task>
              <xr-bag-primitive-type>int</xr-bag-primitive-type>
              <xr-bag-version>1 1</xr-bag-version>
              <type>
                <type-name>Srms-mi-flag-e-b</type-name>
              </type>
            </flag-attached>
          </policy-mi>
        </policy-ipv6-active>
      </policy-ipv6>
    </policy>
  </srms>
  <srlb config="false" is-key="false" node="container" presence="false">
    <xr-path>/oper/srlb/gl/active/</xr-path>
    <xr-xml-map>srms_oper:SRLB</xr-xml-map>
    <xr-task>basic-services</xr-task>
    <srlb-inconsistency config="false" is-key="false" node="container" presence="false">
      <xr-path>/oper/srlb/gl/active/srlb_inconsistency</xr-path>
      <xr-xml-map>srms_oper:SRLBInconsistency</xr-xml-map>
      <xr-task>basic-services</xr-task>
      <xr-bag-grp-name>mpls_lsd_srlb_inconsistency</xr-bag-grp-name>
      <xr-bag>mpls_lsd.bag</xr-bag>
      <start-srlb-range config="false" is-key="false" is-yang-key="false" node="leaf">
        <xr-path>/oper/srlb/gl/active/srlb_inconsistency~mpls_lsd_srlb_inconsistency.StartSrlbRange</xr-path>
        <xr-xml-map>mpls_lsd:StartSrlbRange</xr-xml-map>
        <xr-task>basic-services</xr-task>
        <xr-bag-primitive-type>uint32_t</xr-bag-primitive-type>
        <xr-bag-version>8 0</xr-bag-version>
        <type>
          <type-name>uint32</type-name>
        </type>
      </start-srlb-range>
      <end-srlb-range config="false" is-key="false" is-yang-key="false" node="leaf">
        <xr-path>/oper/srlb/gl/active/srlb_inconsistency~mpls_lsd_srlb_inconsistency.EndSrlbRange</xr-path>
        <xr-xml-map>mpls_lsd:EndSrlbRange</xr-xml-map>
        <xr-task>basic-services</xr-task>
        <xr-bag-primitive-type>uint32_t</xr-bag-primitive-type>
        <xr-bag-version>8 0</xr-bag-version>
        <type>
          <type-name>uint32</type-name>
        </type>
      </end-srlb-range>
    </srlb-inconsistency>
  </srlb>
</Cisco-IOS-XR-segment-routing-ms-oper>
